pyftl/core.cpython-310-x86_64-linux-gnu.so
pyftl/unit.cpython-310-x86_64-linux-gnu.so
fast_pyftl-1.2.0.post2.dist-info/METADATA
fast_pyftl-1.2.0.post2.dist-info/WHEEL
fast_pyftl-1.2.0.post2.dist-info/top_level.txt
fast_pyftl-1.2.0.post2.dist-info/RECORD
