Metadata-Version: 2.1
Name: fast-pyftl
Version: 1.2.0.post2
Summary: PyFTL - Python binding for FTL
Home-page: https://www.fast-corp.co.jp/
Author: FAST CORPORATION
Author-email: support@fast-corp.co.jp
License: UNKNOWN
Platform: UNKNOWN
Classifier: Programming Language :: Python :: 3
Requires-Python: >=3.8
